oq/__init__.py
oq/np.py
oq/pd.py
oq/sk.py
oq/util.py
oq-0.0.3.dist-info/METADATA
oq-0.0.3.dist-info/WHEEL
oq-0.0.3.dist-info/licenses/LICENSE
oq-0.0.3.dist-info/RECORD
