Metadata-Version: 2.4
Name: oq
Version: 0.0.3
Summary: Objects Quickly - AI tools at your finger tips
Project-URL: Homepage, https://github.com/thorwhalen/oq
Project-URL: Repository, https://github.com/thorwhalen/oq
Author: Thor Whalen
License: mit
License-File: LICENSE
Requires-Python: >=3.10
Requires-Dist: config2py>=0.1.44
Requires-Dist: guide>=0.0.8
Provides-Extra: dev
Requires-Dist: pytest-cov>=4.0; extra == 'dev'
Requires-Dist: pytest>=7.0; extra == 'dev'
Requires-Dist: ruff>=0.1.0; extra == 'dev'
Provides-Extra: docs
Requires-Dist: sphinx-rtd-theme>=1.0; extra == 'docs'
Requires-Dist: sphinx>=6.0; extra == 'docs'
